sim_ballena/__init__.py
sim_ballena/sim_ballena.cpython-312-x86_64-linux-gnu.so
sim_ballena-0.1.3.dist-info/METADATA
sim_ballena-0.1.3.dist-info/WHEEL
sim_ballena-0.1.3.dist-info/RECORD
