Metadata-Version: 2.4
Name: sim_ballena
Version: 0.1.3
Classifier: Programming Language :: Rust
Classifier: Programming Language :: Python :: Implementation :: CPython
Classifier: Programming Language :: Python :: Implementation :: PyPy
Summary: Ultra fast SNN simulator for machine learning
Author: Andrés Romo
Requires-Python: >=3.8
